pave/__init__.py
pave/client.py
pave/core/__init__.py
pave/core/api_error.py
pave/core/datetime_utils.py
pave/core/jsonable_encoder.py
pave/core/remove_none_from_headers.py
pave/environment.py
pave/py.typed
pave/resources/__init__.py
pave/resources/cashflow/__init__.py
pave/resources/cashflow/client.py
pave/resources/cashflow/types/__init__.py
pave/resources/cashflow/types/detailed_financial_health_summary.py
pave/resources/cashflow/types/expenditure_tag.py
pave/resources/cashflow/types/fee_tag.py
pave/resources/cashflow/types/get_financial_health_response.py
pave/resources/cashflow/types/get_recurring_expenditures_response.py
pave/resources/cashflow/types/necessity_level.py
pave/resources/cashflow/types/normalized_frequency.py
pave/resources/cashflow/types/recurring_expenditure.py
pave/resources/cashflow/types/top_level_financial_health_summary.py
pave/resources/cashflow/types/transaction.py
fern_pave-0.0.19.dist-info/METADATA
fern_pave-0.0.19.dist-info/WHEEL
fern_pave-0.0.19.dist-info/RECORD
